lexilang/__init__.py
lexilang/detector.py
lexilang/languages.py
lexilang/utils.py
lexilang/data/words.pickle
LexiLang-1.0.4.dist-info/LICENSE
LexiLang-1.0.4.dist-info/METADATA
LexiLang-1.0.4.dist-info/WHEEL
LexiLang-1.0.4.dist-info/top_level.txt
LexiLang-1.0.4.dist-info/RECORD
