Metadata-Version: 2.1
Name: LexiLang
Version: 1.0.4
Summary: Simple, fast dictionary-based language detector
Home-page: https://github.com/LibreTranslate/LexiLang
Author: Piero Toffanin
Author-email: pt@masseranolabs.com
Maintainer: Piero Toffanin
Maintainer-email: pt@masseranolabs.com
License: AGPLv3
Classifier: License :: OSI Approved :: GNU Affero General Public License v3 or later (AGPLv3+)
Classifier: Operating System :: MacOS :: MacOS X
Classifier: Operating System :: Microsoft :: Windows
Classifier: Operating System :: POSIX :: Linux
Classifier: Programming Language :: Python :: 3
Classifier: Programming Language :: Python :: 3.4
Classifier: Programming Language :: Python :: 3.5
Classifier: Programming Language :: Python :: 3.6
Classifier: Programming Language :: Python :: 3.7
Classifier: Intended Audience :: Developers
Classifier: Topic :: Text Processing :: Linguistic
License-File: LICENSE
